hive_kernel/__init__.py
hive_kernel/__main__.py
hive_kernel/install.py
hive_kernel/kernel.py
hive_kernel-0.4.1.dist-info/LICENSE.txt
hive_kernel-0.4.1.dist-info/METADATA
hive_kernel-0.4.1.dist-info/WHEEL
hive_kernel-0.4.1.dist-info/top_level.txt
hive_kernel-0.4.1.dist-info/RECORD
